parlancy/__devel__.py
parlancy/__init__.py
parlancy/base.py
parlancy/filesystem/__init__.py
parlancy/filesystem/path.py
parlancy/filesystem/security.py
parlancy/helpers.py
parlancy/kubernetes/__init__.py
parlancy/kubernetes/aliases.py
parlancy/mcp/__init__.py
parlancy/mcp/aliases.py
parlancy/mcp/proto.py
parlancy/networking/__init__.py
parlancy/networking/aliases.py
parlancy/networking/guards.py
parlancy/software/__init__.py
parlancy/software/aliases.py
parlancy/storage/__init__.py
parlancy/time.py
parlancy-0.1.1.dist-info/WHEEL
parlancy-0.1.1.dist-info/WHEEL.json
parlancy-0.1.1.dist-info/entry_points.txt
parlancy-0.1.1.dist-info/METADATA
parlancy-0.1.1.dist-info/METADATA.json
parlancy-0.1.1.dist-info/RECORD
