Metadata-Version: 2.3
Name: parlancy
Version: 0.1.1
Summary: types, protocols and all things descriptive
Requires-Python: >=3.12
